sbol2/SBOL2Serialize.py
sbol2/__init__.py
sbol2/attachment.py
sbol2/collection.py
sbol2/combinatorialderivation.py
sbol2/component.py
sbol2/componentdefinition.py
sbol2/config.py
sbol2/constants.py
sbol2/dbtl.py
sbol2/document.py
sbol2/experiment.py
sbol2/identified.py
sbol2/implementation.py
sbol2/interaction.py
sbol2/libSBOLj.jar
sbol2/location.py
sbol2/mapsto.py
sbol2/measurement.py
sbol2/model.py
sbol2/module.py
sbol2/moduledefinition.py
sbol2/object.py
sbol2/participation.py
sbol2/partshop.py
sbol2/property.py
sbol2/provo.py
sbol2/sbolerror.py
sbol2/searchquery.py
sbol2/sequence.py
sbol2/sequenceannotation.py
sbol2/sequenceconstraint.py
sbol2/toplevel.py
sbol2/uridict.py
sbol2/validation.py
sbol2/validator.py
sbol2/versionproperty.py
sbol2-1.4.1.dist-info/LICENSE.txt
sbol2-1.4.1.dist-info/METADATA
sbol2-1.4.1.dist-info/WHEEL
sbol2-1.4.1.dist-info/top_level.txt
sbol2-1.4.1.dist-info/RECORD
