Metadata-Version: 2.1
Name: sbol2
Version: 1.4.1
Summary: Pure Python implementation of SBOL 2 standard
Home-page: https://github.com/SynBioDex/pySBOL2
Author: Bryan Bartley
Author-email: editors@sbolstandard.org
License: Apache-2
Keywords: synthetic biology
Platform: UNKNOWN
Classifier: Development Status :: 5 - Production/Stable
Classifier: Intended Audience :: Developers
Classifier: License :: OSI Approved :: Apache Software License
Classifier: Programming Language :: Python :: 3
Requires-Python: >=3.7
License-File: LICENSE.txt
Requires-Dist: rdflib (>=5.0)
Requires-Dist: python-dateutil
Requires-Dist: deprecated
Requires-Dist: lxml
Requires-Dist: requests
Requires-Dist: urllib3
Requires-Dist: packaging (>=20.0)
